CHANGES.rst
LICENSE.txt
MANIFEST.in
README.rst
setup.cfg
setup.py
haufe/__init__.py
haufe.requestmonitoring.egg-info/PKG-INFO
haufe.requestmonitoring.egg-info/SOURCES.txt
haufe.requestmonitoring.egg-info/dependency_links.txt
haufe.requestmonitoring.egg-info/entry_points.txt
haufe.requestmonitoring.egg-info/namespace_packages.txt
haufe.requestmonitoring.egg-info/not-zip-safe
haufe.requestmonitoring.egg-info/requires.txt
haufe.requestmonitoring.egg-info/top_level.txt
haufe/requestmonitoring/DumpTraceback.py
haufe/requestmonitoring/Rotator.py
haufe/requestmonitoring/__init__.py
haufe/requestmonitoring/component.xml
haufe/requestmonitoring/configure.zcml
haufe/requestmonitoring/datatypes.py
haufe/requestmonitoring/info.py
haufe/requestmonitoring/info.zcml
haufe/requestmonitoring/interfaces.py
haufe/requestmonitoring/monitor.py
haufe/requestmonitoring/monitor.zcml
haufe/requestmonitoring/patch.py
haufe/requestmonitoring/successlogging.py
haufe/requestmonitoring/successlogging.zcml
haufe/requestmonitoring/timelogging.py
haufe/requestmonitoring/timelogging.zcml