Metadata-Version: 1.2
Name: haufe.requestmonitoring
Version: 0.6.0
Summary: Zope 2 request monitoring
Home-page: http://github.com/collective/haufe.requestmonitoring
Author: Haufe-Lexware
Author-email: info@zopyx.com
Maintainer: Andreas Jung
Maintainer-email: info@zopyx.com
License: ZPL
Keywords: zope long-running-request monitor logging
Platform: UNKNOWN
Classifier: Development Status :: 5 - Production/Stable
Classifier: Framework :: Plone
Classifier: Framework :: Plone :: 4.3
Classifier: Framework :: Plone :: 5.2
Classifier: License :: OSI Approved :: Zope Public License
Classifier: Programming Language :: Python
Classifier: Programming Language :: Python :: 2
Classifier: Programming Language :: Python :: 2.4
Classifier: Programming Language :: Python :: 2.5
Classifier: Programming Language :: Python :: 2.6
Classifier: Programming Language :: Python :: 2.7
Classifier: Programming Language :: Python :: 3
Classifier: Framework :: Zope2
Classifier: Topic :: System :: Monitoring
Classifier: Topic :: System :: Logging
